{
  "users": [
    {
      "balance": 1841,
      "age": 26,
      "name": "Wallace"
    },
    {
      "balance": 1922,
      "age": 19,
      "name": "Ray"
    },
    {
      "balance": 3749,
      "age": 19,
      "name": "Leah"
    },
    {
      "balance": 2803,
      "age": 26,
      "name": "Barr"
    },
    {
      "balance": 3137,
      "age": 10,
      "name": "Johnson"
    },
    {
      "balance": 1963,
      "age": 13,
      "name": "Carson"
    },
    {
      "balance": 3709,
      "age": 27,
      "name": "Olive"
    },
    {
      "balance": 3499,
      "age": 10,
      "name": "Imogene"
    },
    {
      "balance": 3496,
      "age": 20,
      "name": "Shawna"
    },
    {
      "balance": 3795,
      "age": 27,
      "name": "Juliana"
    },
    {
      "balance": 2836,
      "age": 20,
      "name": "Herring"
    },
    {
      "balance": 1313,
      "age": 26,
      "name": "Cardenas"
    },
    {
      "balance": 3021,
      "age": 22,
      "name": "Holman"
    },
    {
      "balance": 3277,
      "age": 25,
      "name": "Edwina"
    },
    {
      "balance": 3221,
      "age": 24,
      "name": "Lourdes"
    },
    {
      "balance": 2068,
      "age": 13,
      "name": "Mcgee"
    },
    {
      "balance": 3722,
      "age": 16,
      "name": "Cathleen"
    },
    {
      "balance": 1305,
      "age": 22,
      "name": "Flossie"
    },
    {
      "balance": 2612,
      "age": 15,
      "name": "Amelia"
    },
    {
      "balance": 1473,
      "age": 11,
      "name": "Claire"
    },
    {
      "balance": 3625,
      "age": 23,
      "name": "Bass"
    },
    {
      "balance": 3476,
      "age": 24,
      "name": "Suzanne"
    },
    {
      "balance": 1782,
      "age": 12,
      "name": "Santana"
    },
    {
      "balance": 1174,
      "age": 10,
      "name": "Tracie"
    },
    {
      "balance": 3288,
      "age": 18,
      "name": "Sandra"
    },
    {
      "balance": 1485,
      "age": 23,
      "name": "Garza"
    },
    {
      "balance": 3919,
      "age": 14,
      "name": "Fran"
    },
    {
      "balance": 3770,
      "age": 14,
      "name": "Jefferson"
    },
    {
      "balance": 3178,
      "age": 29,
      "name": "Johnston"
    },
    {
      "balance": 1967,
      "age": 10,
      "name": "Clemons"
    },
    {
      "balance": 2083,
      "age": 13,
      "name": "Berg"
    },
    {
      "balance": 3599,
      "age": 16,
      "name": "Mcbride"
    },
    {
      "balance": 1454,
      "age": 20,
      "name": "Penny"
    },
    {
      "balance": 2137,
      "age": 12,
      "name": "Charlotte"
    },
    {
      "balance": 2252,
      "age": 22,
      "name": "Luna"
    },
    {
      "balance": 2655,
      "age": 27,
      "name": "Mueller"
    },
    {
      "balance": 2440,
      "age": 10,
      "name": "Lakeisha"
    },
    {
      "balance": 1978,
      "age": 18,
      "name": "Castro"
    },
    {
      "balance": 2795,
      "age": 28,
      "name": "Pansy"
    },
    {
      "balance": 2739,
      "age": 11,
      "name": "Mae"
    },
    {
      "balance": 1702,
      "age": 24,
      "name": "Rivas"
    },
    {
      "balance": 1352,
      "age": 13,
      "name": "Queen"
    },
    {
      "balance": 3849,
      "age": 20,
      "name": "Lottie"
    },
    {
      "balance": 2747,
      "age": 21,
      "name": "Marcella"
    }
  ]
}
